slices/__init__.py
slices/config.py
slices/core.py
slices/nlopt.h
slices/tobascco_net.py
slices/utils.py
slices/utils_wyckoff.py
slices/xtb_noring_nooutput_nostdout_noCN
slices/MP-2021.2.8-EFS/checkpoint
slices/MP-2021.2.8-EFS/m3gnet.data-00000-of-00001
slices/MP-2021.2.8-EFS/m3gnet.index
slices/MP-2021.2.8-EFS/m3gnet.json
slices-2.0.12.dist-info/licenses/LICENSE
slices-2.0.12.dist-info/METADATA
slices-2.0.12.dist-info/WHEEL
slices-2.0.12.dist-info/top_level.txt
slices-2.0.12.dist-info/RECORD
