Metadata-Version: 2.4
Name: slices
Version: 2.0.12
Author-email: Hang Xiao <xiaohang07@live.cn>
Requires-Python: >=3.9
License-File: LICENSE
Requires-Dist: setuptools>=18.0
Requires-Dist: m3gnet==0.2.4
Requires-Dist: smact==2.5.5
Dynamic: license-file
